{
  "last_run": "2026-04-12T09:17:22.020930",
  "entries": [
    {
      "id": "2026-04-12",
      "date_sort": "2026-04-07",
      "week_tag": "Week of 7 Apr",
      "date_label": "7 &ndash; 7 April 2026",
      "summary_html": "<p>In the latest dev session, we made some cool tweaks to Ritual & Ruin that should brighten up your experience! The chunk floor shader got a much-needed fix for those annoying white streaks that used to appear when moving around. We shifted our shadow calculations to work on a per-pixel basis, meaning smoother and more seamless shadows across the game world—no more glaring stripes where they shouldn't be!</p>\n                <p>We've also pushed Ritual & Ruin further into its dark kawaii aesthetic, which you might recognize as having that distinct anime vibe. The floor tiles now have a more dramatic contrast with near-white tops accented by violet hints, and darker sides bordered in dim purple grout. It's all about striking a balance between the cute and the mysterious.</p>\n                <p>On top of these changes, we've polished up the jellyfish players. They're sporting longer tentacles that extend their reach within matches, making every move more pronounced. Plus, they've become more visible against darker floors with increased opacity—so no more squinting to spot your jellyfish on the battlefield! All these tweaks aim to make the visuals pop while ensuring everything looks sharp and cohesive. Can't wait for you all to see how it turns out in action!</p>",
      "raw_html": "<h3>2026-04-07 — Chunk Floor Shader, Shadow Fix, Visual Polish</h3>\n                  <h3>Summary</h3>\n                  <p>Fixed a persistent white-streak artifact on the chunk floor shader, iterated on the dark kawaii visual direction, and polished jellyfish player visuals.</p>\n                  <h3>Dark Kawaii Visual Direction</h3>\n                  <p>Iterated the ChunkFloorTile shader toward a dark kawaii / anime aesthetic:</p>\n                  <ul>\n                    <li><strong>Top face</strong>: near-white tiles with violet hint (<code>0.93, 0.90, 1.00</code>) + neon lavender grout (<code>0.72, 0.38, 0.95</code>) with glow emission</li>\n                    <li><strong>Side faces</strong>: near-black tiles (<code>0.05, 0.05, 0.09</code>) + dim purple grout (<code>0.48, 0.36, 0.70</code>)</li>\n                    <li><strong>Face detection</strong>: branchless <code>yDom = step(absNorm.x, absNorm.y) * step(absNorm.z, absNorm.y)</code> drives both color palettes</li>\n                    <li><strong>Degradation</strong>: Voronoi crack lines with pink/magenta glow (<code>0.95, 0.18, 0.62</code>), FBM staining, mold growth</li>\n                    <li><strong>Crack scale</strong>: lowered <code>_CrackScale</code> to 0.5 (few large cracks rather than fine network)</li>\n                    <li><strong>Tile scale</strong>: doubled <code>_TileScale</code> to 1.0 (larger tiles)</li>\n                    <li><strong>Cel shading</strong>: <code>floor(NdotL * bands) / (bands - 1)</code> quantized diffuse, 3 bands</li>\n                  </ul>\n                  <p>---</p>\n                  <h3>Visual Polish</h3>\n                  <h3>Jellyfish Tentacles — Longer</h3>\n                  <ul>\n                    <li><code>segmentLength</code>: <code>0.15</code> → <code>0.35</code> (scale=1 normalized, auto-scaled at runtime)</li>\n                    <li>At match scale=0.25: total tentacle reach ≈ 0.525 world units (was 0.225)</li>\n                  </ul>\n                  <h3>Jellyfish Body — More Opaque</h3>\n                  <ul>\n                    <li><code>_Opacity</code> in <code>JellyfishBody.mat</code>: <code>0.18</code> → <code>0.65</code></li>\n                    <li>Players are now clearly visible against the dark floor</li>\n                  </ul>\n                  <p>---</p>\n                  <h3>Files Changed</h3>\n                  <ul>\n                    <li><code>Assets/ProtoV2/Shaders/ChunkFloorTile.shader</code> — per-fragment shadow coord, dark kawaii style</li>\n                    <li><code>Assets/ProtoV2/Materials/ChunkFloorTile.mat</code> — color values for dark kawaii look</li>\n                    <li><code>Assets/ProtoV2/Scripts/JellyfishVisuals.cs</code> — segmentLength 0.15→0.35</li>\n                    <li><code>Assets/ProtoV2/Materials/JellyfishBody.mat</code> — _Opacity 0.18→0.65</li>\n                  </ul>"
    },
    {
      "id": "2026-04-05",
      "date_sort": "2026-04-04",
      "week_tag": "Week of 29 Mar",
      "date_label": "29 Mar &ndash; 4 Apr 2026",
      "summary_html": "<p>### Summary of Recent Changes and Developments</p>\n                <p>#### Jellyfish Tentacle Reversion (2026-04-03)</p>\n                <p>**Issue:**\n- The implementation of ObiRope tentacles for jellyfish caused excessive bouncing during bell pulses, as they reacted to the physics of the visual root squishing.</p>\n                <p>**Solution:**\n- Reverted to using a LineRenderer spring-chain setup.\n- Adjusted segment lengths and scaling to ensure visibility across different character scales (e.g., match scale 0.25, lobby scale 0.69).</p>\n                <p>**Implementation Details:**\n- Each tentacle consists of six segments that maintain proper spacing and length.\n- Size values are dynamically adjusted using `transform.lossyScale.x` for consistent appearance at varying scales.</p>\n                <p>#### Tilt Control Enhancements (2026-04-04)</p>\n                <p>**Objective:**\n- Complete integration of tilt control in various UI elements and settings, addressing gaps from a previous session.</p>\n                <p>**Key Changes:**</p>\n                <p>1. **Tilt in Rebind UIs:**\n   - Added \"Tilt\" to the rebindable actions in `InputRebindMenuUI` and `PlayerSettingsPanel`.\n   - Updated `InputRebindUIController` for controller presets, ensuring correct bindings across different control schemes.</p>\n                <p>2. **Auto-Tilt Toggle Wiring:**\n   - Confirmed existing wiring via `PlayerMenuSetupWizard`, ensuring functionality is intact.\n   - The toggle is accessible only to controller players and adjusts based on their input mode (visible in the settings panel accessed through menu).</p>\n                <p>3. **Per-Player Menu Hint Text:**\n   - Introduced a new UI prompt system to guide players on accessing settings during a match.\n   - Updated `PlayerMenuController` to dynamically display hint text based on game state and player device.\n   - Enhanced `PlayerSettingsPanel` with instruction text for closing settings.</p>\n                <p>**Editor Wiring:**\n- Utilized `MenuHintWiringWizard` to automate the setup of menu hint texts in both the PlayerPrefab and LobbyScene, ensuring consistent UI elements across scenes.</p>\n                <p>### Architectural Insights</p>\n                <p>- **Tentacle Implementation:** Ensures visual consistency by auto-scaling and maintaining visibility across different game modes.\n- **Tilt Control Integration:** Provides a seamless experience for players using controllers, with clear guidance through dynamic hint texts.\n- **UI Consistency:** Automated wiring scripts ensure that UI elements are correctly set up and maintained, reducing manual errors.</p>\n                <p>These updates collectively enhance the player experience by refining visual effects and improving control accessibility, ensuring a smoother gameplay interaction across various modes and devices.</p>",
      "raw_html": "<h3>2026-03-29 — SFX Options for All Assigned Slots</h3>\n                  <h3>Summary</h3>\n                  <p>Added alternative option files for every currently-assigned SFX slot so the user can audition and swap without losing the existing working sounds.</p>\n                  <h3>AUDIO.md</h3>\n                  <p>Added <code>## SFX Options — Assigned Slots (Alternatives)</code> section to <code>playinstigator_docs/Games/Ritual & Ruin/AUDIO.md</code> with per-slot tables listing all downloaded files and Freesound URLs.</p>\n                  <p>---</p>\n                  <h3>Next Steps</h3>\n                  <ul>\n                    <li>Open Unity, navigate to <code>Assets/ProtoV2/Audio/SFX/Options/</code> in Project window</li>\n                    <li>Audition each folder to find preferred alternatives</li>\n                    <li>Copy chosen file to correct <code>SFX/</code> subfolder, rename, re-assign in Inspector</li>\n                  </ul>\n                  <p>---</p>\n                  <h3>2026-03-29 — Audio Variation System + SFX Options</h3>\n                  <h3>Summary</h3>\n                  <p>Built centralized audio variation system and sourced replacement options for all unassigned SFX slots.</p>\n                  <p>---</p>\n                  <h3>AudioVariation System</h3>\n                  <p>Created <code>Assets/ProtoV2/Scripts/Audio/AudioVariation.cs</code> — a single <code>[Serializable]</code> class embedded in every audio script as one Inspector foldout. Replaces the scattered per-script variation fields that were being duplicated.</p>\n                  <p><strong>Parameters:</strong> pitch ±, volume ±, startTime (random clip offset), low-pass cutoff ±, reverb ±</p>\n                  <p><strong>Methods:</strong></p>\n                  <ul>\n                    <li><code>Init(go)</code> — called in Awake, caches <code>AudioLowPassFilter</code> / <code>AudioReverbFilter</code> if present</li>\n                    <li><code>PlayOneShot(source, clip, vol)</code> — variation + PlayOneShot</li>\n                    <li><code>PlayLoop(source, clip, vol)</code> — variation + pitch/filter + Play() with loop=true</li>\n                    <li><code>PlayFromOffset(source, clip, vol)</code> — variation + startTime + Play() non-looping (throttled impacts)</li>\n                  </ul>\n                  <p>All 6 audio scripts updated to use it: <code>AudioManager</code>, <code>PlayerAudioSource</code>, <code>AltarAudioSource</code>, <code>BloodEmitterAudioSource</code> (two instances — loop + burst), <code>FloorImpactAudio</code>, <code>UIAudioManager</code>.</p>\n                  <p><strong>Bug fixed:</strong> <code>FloorImpactAudio.SharedImpactClip</code> was never being set at runtime — floor blood impacts were silent. Fixed by adding <code>bloodImpactClip</code> field to <code>AudioManager</code> and wiring the static in <code>Awake()</code>. Requires assigning <code>blood_impact.ogg</code> to the new \"Floor Impact\" field on the AudioManager GO in Inspector.</p>\n                  <p>---</p>\n                  <h3>SFX Audit</h3>\n                  <p>Checked which audio slots are actually assigned vs. missing. Found that several \"removed\" clips still have files on disk but are unassigned in the Inspector:</p>\n                  <p>| Slot | File | Status |</p>\n                  <p>|---|---|---|</p>\n                  <p>| <code>deathClip</code> | <code>SFX/Character/player_death.ogg</code> | Exists but unsuitable |</p>\n                  <p>| <code>formTransformClip</code> | <code>SFX/Character/form_transform.ogg</code> | Exists but unsuitable |</p>\n                  <p>| <code>flowLoopClip</code> | <code>SFX/Fluid/emitter_flow.ogg</code> | Exists but unsuitable |</p>\n                  <p>| All 5 UIAudioManager clips | <code>SFX/UI/*.ogg</code> | Exist but unsuitable |</p>\n                  <p>---</p>\n                  <h3>SFX Options Downloaded</h3>\n                  <p>Downloaded and organised replacement options to <code>Assets/ProtoV2/Audio/SFX/Options/</code>:</p>\n                  <p>| Folder | Files | Sources |</p>\n                  <p>|---|---|---|</p>\n                  <p>| <code>Options/Death/</code> | 9 | Kenney Sci-Fi Sounds (slime, explosionCrunch), Kenney Impact Sounds (impactSoft_heavy) |</p>\n                  <p>| <code>Options/Transform/</code> | 8 | Kenney Sci-Fi Sounds (forceField x5, computerNoise x2) |</p>\n                  <p>| <code>Options/FlowLoop/</code> | 9 | Kenney Sci-Fi Sounds (spaceEngineLow, engineCircular, spaceEngineSmall) |</p>\n                  <p>| <code>Options/UI_Click/</code> | 11 | Kenney Interface Sounds (click x5), Kenney UI Audio (click x5, mouseclick) |</p>\n                  <p>| <code>Options/UI_Hover/</code> | 12 | Kenney UI Audio (rollover x6), Kenney Interface Sounds (scroll x4, tick x2) |</p>\n                  <p>| <code>Options/UI_Pause/</code> | 15 | Kenney Interface Sounds (toggle x4, switch x7, open x2, close x2) |</p>\n                  <p>| <code>Options/UI_PlayerJoin/</code> | 7 | Kenney Interface Sounds (confirmation x4, bong, pluck x2) |</p>\n                  <p>| <code>Options/UI_Transition/</code> | 9 | Kenney Interface Sounds (maximize x5, glitch x4) |</p>\n                  <p>All Kenney files are CC0. Total: 80 auditionable options across 8 slots.</p>\n                  <p>Additional Freesound CC0 and Pixabay options (40+ more) documented in <code>AUDIO.md</code> with direct URLs for manual download (Freesound requires login).</p>\n                  <p>---</p>\n                  <h3>AUDIO.md Updated</h3>\n                  <p><code>playinstigator_docs/Games/Ritual & Ruin/AUDIO.md</code> updated with:</p>\n                  <ul>\n                    <li>Corrected slot statuses (file-exists-but-unsuitable vs. truly unassigned)</li>\n                    <li>Full Options section per slot — downloaded files + manual-download Freesound/Pixabay links</li>\n                    <li>How-to-assign workflow</li>\n                    <li>Credits table updated with Kenney Sci-Fi Sounds and Impact Sounds</li>\n                  </ul>\n                  <p>---</p>\n                  <h3>Next Steps</h3>\n                  <ul>\n                    <li>Audition Options files in Unity, pick one per slot, rename and assign in Inspector</li>\n                    <li>Assign <code>blood_impact.ogg</code> to AudioManager GO's \"Floor Impact\" field (fix for silent floor impacts)</li>\n                    <li>For slots where no Kenney option feels right: download preferred Freesound/Pixabay option using the URLs in AUDIO.md</li>\n                  </ul>\n                  <p>---</p>\n                  <h3>Evolution Size Fix + Asset Catalog + Resolved Issue Cleanup (2026-03-29)</h3>\n                  <p>---</p>\n                  <h3>1. Terminal Evolution Size Fix</h3>\n                  <h3>Issue</h3>\n                  <p>Terminal evolution (Tier 2) scale multiplier of 1.5× made the jellyfish too large to pass through floor holes.</p>\n                  <h3>Fix</h3>\n                  <p><strong>File:</strong> <code>Assets/ProtoV2/Scripts/JellyfishVisuals.cs</code> — line 194</p>\n                  <p><strong>Scale progression (final):</strong></p>\n                  <p>| Tier | Scale | Visual cues |</p>\n                  <p>|---|---|---|</p>\n                  <p>| Base (0) | 1.0× | White tint, squish 0.20 |</p>\n                  <p>| Enhanced (1) | 1.2× | Blue tint, squish 0.28 |</p>\n                  <p>| Terminal (2) | 1.3× | Gold tint, squish 0.38, pulse 0.75× faster |</p>\n                  <p>Terminal is still visually distinct (gold color, faster pulse, more squish, slightly larger) but now fits through floor holes.</p>\n                  <p>---</p>\n                  <h3>2. Resolved Issues Cleanup</h3>\n                  <p>Removed the following items from the open blockers list — all confirmed resolved:</p>\n                  <ul>\n                    <li><strong>TQ-4 (Pause + ObiFluid)</strong>: ObiFluid particles correctly pause/resume with <code>Time.timeScale = 0</code>. No code changes needed.</li>\n                    <li><strong>maxSurfaceChunks</strong>: Already reduced to 2000 in ObiSolver Inspector. No further action needed.</li>\n                    <li><strong>ObiNativeList finalizer</strong>: Mitigated by D3D11 (GPU buffers handled more gracefully). Lower priority, not blocking.</li>\n                  </ul>\n                  <p>Open blockers: <strong>None.</strong></p>\n                  <p>---</p>\n                  <h3>3. Asset Catalog</h3>\n                  <p>Created <code>Confirmed/strategy/Asset Catalog.md</code> — full inventory of 38 purchased Unity assets with applicability ratings for Ritual & Ruin.</p>\n                  <p><strong>Summary:</strong></p>\n                  <ul>\n                    <li><strong>Tier 1 (use these):</strong> Feel, Amplify Shader Editor, Amplify Shader Pack, Obi Rope, Obi Softbody, Motion Blur, Magic Effects FREE, DOTween</li>\n                    <li><strong>Tier 2 (potentially useful):</strong> Elemental Spells VFX, Easy Save, KayKit Platformer Pack, Weather Maker, Fantasy RPG GUI, Obi Cloth</li>\n                    <li><strong>Tier 3 (not relevant):</strong> Humanoid character packs, city environments, turret assets, tank, fruit market, 2D tools</li>\n                  </ul>\n                  <p><strong>Priority integration order:</strong> Feel → Obi Rope → Motion Blur → Magic Effects FREE → Easy Save → Amplify Shader Editor</p>\n                  <p>---</p>\n                  <h3>4. Evolution Visual Distinction — Next Steps</h3>\n                  <p>Current visual distinction between tiers (post-fix):</p>\n                  <ul>\n                    <li>Size: 1.0 → 1.2 → 1.3 (subtle)</li>\n                    <li>Color: white → blue → gold ✅ clear</li>\n                    <li>Squish: 0.20 → 0.28 → 0.38 (subtle)</li>\n                    <li>Pulse rate: unchanged → unchanged → 0.75× faster ✅ readable</li>\n                  </ul>\n                  <p><strong>Suggested enhancements using owned assets:</strong></p>\n                  <ul>\n                    <li><strong>Feel</strong>: Add camera shake burst + flash on evolution event (<code>OnEvolution</code> subscriber)</li>\n                    <li><strong>Magic Effects FREE</strong>: Spawn a VFX burst prefab at player position on evolution</li>\n                    <li><strong>Obi Rope</strong>: Upgrade tentacles to physical simulation (more dramatic swing on evolution)</li>\n                    <li><strong>Amplify Shader Editor</strong>: Add emissive glow increase per tier to jellyfish bell material</li>\n                  </ul>\n                  <p>Design discussion needed on which to prioritize.</p>\n                  <p>---</p>\n                  <h3>Jellyfish Squish + Emitter Indicator + Scroll Camera Fix (2026-03-29)</h3>\n                  <p>---</p>\n                  <h3>1. Jellyfish Cap Horizontal Squish</h3>\n                  <h3>Issue</h3>\n                  <p>XZ bulge on pulse was 30% of squish amount — too subtle.</p>\n                  <h3>Fix</h3>\n                  <p><strong>File:</strong> <code>Assets/ProtoV2/Scripts/JellyfishVisuals.cs</code></p>\n                  <p>XZ bulge doubled — bell now visibly widens on each pulse. Spring recovery unchanged.</p>\n                  <p>---</p>\n                  <h3>2. Emitter Indicator — No Longer Lands on Players</h3>\n                  <h3>Issue</h3>\n                  <p><code>BloodEmitterIndicator.DrawCircle()</code> used <code>Physics.Raycast</code> with no layer filter. When a player flew between the emitter and the floor, the raycast hit the player's collider, placing the circle on top of the player.</p>\n                  <h3>Root Cause</h3>\n                  <p>All objects (players, floors, walls) are on the Default layer — no layer separation to filter against.</p>\n                  <h3>Fix</h3>\n                  <p><strong>File:</strong> <code>Assets/ProtoV2/Scripts/BloodSystem/BloodEmitterIndicator.cs</code></p>\n                  <p>Replaced physics raycast entirely with chunk-coordinate lookup. We already know the grid layout — no need to cast rays:</p>\n                  <p>Walks top→middle→bottom floor. Finds first floor that has a solid chunk at the emitter's XZ grid position. Surface Y derived from floor root + ChunkHeight/2. Removed <code>raycastLength</code> field entirely.</p>\n                  <p>---</p>\n                  <h3>3. Camera Scroll — Single Source of Truth for Floor Spacing</h3>\n                  <h3>Issue</h3>\n                  <p><code>ScrollingFloorCamera</code> had its own <code>[SerializeField] float floorVerticalSpacing = 5f</code> independent from <code>FloorManager.floorVerticalSpacing</code>. If the two values differed in the Inspector, the camera would scroll to the wrong Y position.</p>\n                  <h3>Fix</h3>\n                  <p><strong>File:</strong> <code>Assets/ProtoV2/Scripts/CameraSystem/ScrollingFloorCamera.cs</code> — <code>CalculateFloorYPosition()</code></p>\n                  <p>Camera's own <code>floorVerticalSpacing</code> field is now only a fallback for editor gizmos. At runtime, both floor generation and camera scroll use the same value from FloorManager.</p>\n                  <h3>Current values (defaults)</h3>\n                  <ul>\n                    <li><code>FloorManager.floorVerticalSpacing</code> = 5f — adjust this to change floor spacing</li>\n                    <li><code>ScrollingFloorCamera.scrollDuration</code> = 2.5f — how long the scroll animation takes</li>\n                  </ul>\n                  <p>---</p>\n                  <h3>4. Ritual Completion VFX — AltarVFXController</h3>\n                  <h3>Status</h3>\n                  <p>Feel (More Mountains) and Magic Effects FREE (Hovl Studio) are now imported.</p>\n                  <h3>New File</h3>\n                  <p><strong><code>Assets/ProtoV2/Scripts/BloodSystem/AltarVFXController.cs</code></strong> — attach alongside <code>AltarParticleConsumer</code> on the Altar prefab.</p>\n                  <p>Drives:</p>\n                  <ul>\n                    <li><code>OnMeterFull</code> → spawn looping countdown VFX (e.g. <code>Magic circle.prefab</code> or <code>Healing circle.prefab</code>)</li>\n                    <li><code>OnRitualComplete</code> → destroy countdown VFX + spawn completion burst (e.g. <code>Red energy explosion.prefab</code>) + play <code>MMF_Player</code> feedbacks (screen shake, flash, audio)</li>\n                    <li><code>OnAltarReset</code> → destroy countdown VFX</li>\n                  </ul>\n                  <h3>Inspector Wiring Required (on Altar prefab)</h3>\n                  <p>1. Add <code>AltarVFXController</code> component</p>\n                  <p>2. Create child GO with <code>MMF_Player</code>, add Screen Shake + Camera Flash + Audio feedbacks → assign to <code>completionFeedbacks</code></p>\n                  <p>3. Assign <code>completionVFXPrefab</code> = <code>Red energy explosion.prefab</code> (Hovl Studio Magic Effects)</p>\n                  <p>4. Assign <code>countdownVFXPrefab</code> = <code>Magic circle.prefab</code> or <code>Healing circle.prefab</code></p>\n                  <p>5. Tune <code>completionVFXYOffset</code> and <code>countdownVFXYOffset</code> to sit correctly at altar ground level</p>\n                  <h3>Also Available</h3>\n                  <ul>\n                    <li><strong>Elemental Spells Full Pack VFX</strong> — still in <code>.unitypackage</code> archive, not yet imported. Contains additional burst/explosion options for ritual completion.</li>\n                  </ul>\n                  <p>---</p>\n                  <h3>5. Lobby Scene — Tentacle Scale Fix</h3>\n                  <h3>Issue</h3>\n                  <p><code>JellyfishVisuals</code> tentacle rim positions were set in world-space Inspector values. <code>characterScale</code> in LobbyScene was <code>1.0</code> while MatchScene uses <code>0.25</code>. At scale 1, the bell is 4× larger than the rim radius (0.4), so tentacles appeared hidden inside the player body.</p>\n                  <h3>Fix — Two Parts</h3>\n                  <p><strong>Part A:</strong> <code>LobbyScene.unity</code> — <code>MultiplayerManager.characterScale</code> changed <code>1</code> → <code>0.25</code> so all scenes use the same scale.</p>\n                  <p><strong>Part B:</strong> <code>JellyfishVisuals.cs</code> — <code>BuildTentacles()</code> and <code>UpdateTentacles()</code> now multiply all spatial values by <code>transform.lossyScale.x</code> (<code>ws</code>):</p>\n                  <p>Inspector values are now <strong>local-space</strong> (as if characterScale = 1). <code>ws</code> scales them to world-space at runtime, so tentacles are always proportionally correct regardless of <code>characterScale</code>.</p>\n                  <p><strong>Part C:</strong> <code>PlayerPrefab.prefab</code> Inspector values converted from old world-space to new local-space (÷ 0.25 = × 4):</p>\n                  <p>| Field | Before (world-space) | After (local-space) |</p>\n                  <p>|---|---|---|</p>\n                  <p>| <code>rimRadius</code> | 0.4 | 1.6 |</p>\n                  <p>| <code>rimY</code> | 0.56 | 2.24 |</p>\n                  <p>| <code>segmentLength</code> | 0.15 | 0.6 |</p>\n                  <p>| <code>startWidth</code> | 0.15 | 0.6 |</p>\n                  <p>| <code>endWidth</code> | 0.04 | 0.16 |</p>\n                  <p>At <code>characterScale = 0.25</code>, <code>ws = 0.25</code>, so effective world-space values are identical to before.</p>\n                  <p>---</p>\n                  <h3>Dev Log — 2026-03-29 — MMFeedbacks Integration</h3>\n                  <h3>Summary</h3>\n                  <p>Full MMFeedbacks (Feel) integration across all major gameplay events in Ritual & Ruin. Every significant player action, match event, and altar moment now triggers camera shake and/or freeze-frame feedback.</p>\n                  <p>---</p>\n                  <h3>What Was Done</h3>\n                  <h3>AltarVFXController — Namespace Fix</h3>\n                  <ul>\n                    <li><strong>File</strong>: <code>Assets/ProtoV2/Scripts/BloodSystem/AltarVFXController.cs</code></li>\n                    <li>Added <code>using CupFairy.BloodSystem;</code> to fix CS0246 compile error (<code>AltarParticleConsumer</code> not found)</li>\n                    <li>Controller was already written; this unblocked it from compiling</li>\n                  </ul>\n                  <h3>Script Changes — MMF_Player Fields Added</h3>\n                  <p>All scripts received <code>using MoreMountains.Feedbacks;</code> + a <code>[SerializeField] private MMF_Player</code> field + a <code>?.PlayFeedbacks(transform.position)</code> call at the relevant event moment:</p>\n                  <p>| Script | Field | Trigger |</p>\n                  <p>|---|---|---|</p>\n                  <p>| <code>DeathHandler.cs</code> | <code>deathFeedback</code> | Before <code>OnDied?.Invoke()</code> |</p>\n                  <p>| <code>UnifiedBar.cs</code> | <code>evolutionFeedback</code> | Before <code>OnEvolution?.Invoke()</code> in <code>TriggerEvolution()</code> |</p>\n                  <p>| <code>CharacterController1.cs</code> | <code>pulseFeedback</code> | After <code>PulsedThisFrame = true</code> in pulse timer |</p>\n                  <p>| <code>TransformController.cs</code> | <code>formToggleFeedback</code> | At start of <code>Toggle()</code> |</p>\n                  <p>| <code>MatchCountdown.cs</code> | <code>countdownBeatFeedback</code>, <code>goFeedback</code> | Each countdown beat tick; GO! display |</p>\n                  <p>| <code>MatchManager.cs</code> | <code>teamEliminatedFeedback</code>, <code>matchEndFeedback</code> | <code>RecordTeamEliminated()</code>; <code>EndMatch()</code> |</p>\n                  <h3>PlayerPrefab — 4 Feedback Child GOs</h3>\n                  <p>Added 4 new child GameObjects under the PlayerPrefab root, each with a Transform + MMF_Player component:</p>\n                  <p>| GO Name | fileID | Wired to Script Field | Feedbacks |</p>\n                  <p>|---|---|---|---|</p>\n                  <p>| <code>DeathFeedbacks</code> | &1111111111111111103 | <code>DeathHandler.deathFeedback</code> | FreezeFrame 0.08s + PositionShake 0.4s/range 0.5 |</p>\n                  <p>| <code>EvolutionFeedbacks</code> | &1111111111111111106 | <code>UnifiedBar.evolutionFeedback</code> | FreezeFrame 0.05s + PositionShake 0.3s/range 0.3 |</p>\n                  <p>| <code>PulseFeedbacks</code> | &1111111111111111109 | <code>CharacterController1.pulseFeedback</code> | PositionShake 0.1s/range 0.05 (subtle — fires every 0.35s) |</p>\n                  <p>| <code>FormToggleFeedbacks</code> | &1111111111111111112 | <code>TransformController.formToggleFeedback</code> | PositionShake 0.2s/range 0.15 |</p>\n                  <p>All 4 Transform fileIDs (1111111111111111102, 105, 108, 111) added to root Transform <code>m_Children</code> list (fileID 5020478598309948295).</p>\n                  <h3>MatchScene — 4 Feedback Child GOs + Scene Components</h3>\n                  <p>Previously added (pre-this-session):</p>\n                  <ul>\n                    <li><code>MMPositionShaker</code> on Main Camera</li>\n                    <li><code>MMTimeManager</code> GO in scene</li>\n                    <li>4 feedback child GOs under MatchCountdown and MatchManager</li>\n                  </ul>\n                  <p>This session — populated the MMF_Player feedbacks in each GO:</p>\n                  <p>| GO Name | fileID | Wired to Script Field | Feedbacks |</p>\n                  <p>|---|---|---|---|</p>\n                  <p>| <code>CountdownBeatFeedbacks</code> | &1482767222 | <code>MatchCountdown.countdownBeatFeedback</code> | PositionShake 0.1s/range 0.1 |</p>\n                  <p>| <code>GoFeedbacks</code> | &872176054 | <code>MatchCountdown.goFeedback</code> | FreezeFrame 0.05s + PositionShake 0.3s/range 0.3 |</p>\n                  <p>| <code>TeamEliminatedFeedbacks</code> | &247481994 | <code>MatchManager.teamEliminatedFeedback</code> | FreezeFrame 0.06s + PositionShake 0.35s/range 0.4 |</p>\n                  <p>| <code>MatchEndFeedbacks</code> | &1200068797 | <code>MatchManager.matchEndFeedback</code> | FreezeFrame 0.1s + PositionShake 0.5s/range 0.5 |</p>\n                  <h3>Altar Prefab — Completion Feedbacks (Previous Session)</h3>\n                  <p>Already done: <code>CompletionFeedbacks</code> child MMF_Player has:</p>\n                  <ul>\n                    <li>MMF_Light (existing)</li>\n                    <li>MMF_FreezeFrame (0.05s)</li>\n                    <li>MMF_PositionShake (0.3s/range 0.3, random XY)</li>\n                  </ul>\n                  <p>---</p>\n                  <h3>Feedback Intensity Rationale</h3>\n                  <p>| Event | Intensity | Reasoning |</p>\n                  <p>|---|---|---|</p>\n                  <p>| Match end | Strongest (0.1s freeze, 0.5 shake) | Game-ending moment, maximum impact |</p>\n                  <p>| Player death | Strong (0.08s freeze, 0.5 shake) | High-stakes moment |</p>\n                  <p>| Team eliminated | Medium-strong (0.06s freeze, 0.4 shake) | Significant match event |</p>\n                  <p>| GO! start | Medium (0.05s freeze, 0.3 shake) | Match start signal |</p>\n                  <p>| Evolution | Medium (0.05s freeze, 0.3 shake) | Power-up moment |</p>\n                  <p>| Altar completion | Medium (0.05s freeze, 0.3 shake) | Ritual payoff |</p>\n                  <p>| Form toggle | Subtle (0.2s shake/0.15 range) | Frequent action, shouldn't fatigue |</p>\n                  <p>| Countdown beat | Subtle (0.1s shake/0.1 range) | Rhythmic, very frequent |</p>\n                  <p>| Staccato pulse | Minimal (0.1s shake/0.05 range) | Fires every 0.35s, must be imperceptible individually |</p>\n                  <p>---</p>\n                  <h3>Technical Notes</h3>\n                  <ul>\n                    <li>All feedbacks use <code>managed reference</code> YAML format (<code>FeedbacksList:</code> + <code>references: RefIds:</code>) required by MMF_Player v3</li>\n                    <li>Scene MMF_Players use a hybrid format (<code>Feedbacks: []</code> legacy field + <code>FeedbacksList:</code> + <code>references:</code>) — both must be present</li>\n                    <li><code>MMTimeManager</code> GO required in scene for FreezeFrame to function (timescale manipulation)</li>\n                    <li><code>MMPositionShaker</code> on Camera required to receive PositionShake events (channel 0)</li>\n                    <li><code>Owner</code> field in each feedback data points to the MMF_Player component's own fileID</li>\n                    <li>All PositionShake feedbacks: <code>RandomizeDirectionX: 1</code>, <code>RandomizeDirectionY: 1</code>, <code>RandomizeDirectionZ: 0</code> (2D shake only, no depth)</li>\n                  </ul>\n                  <p>---</p>\n                  <h3>Files Modified</h3>\n                  <ul>\n                    <li><code>Assets/ProtoV2/Scripts/BloodSystem/AltarVFXController.cs</code></li>\n                    <li><code>Assets/ProtoV2/Scripts/DeathHandler.cs</code></li>\n                    <li><code>Assets/ProtoV2/Scripts/UnifiedBar.cs</code></li>\n                    <li><code>Assets/ProtoV2/Scripts/CharacterController1.cs</code></li>\n                    <li><code>Assets/ProtoV2/Scripts/TransformController.cs</code></li>\n                    <li><code>Assets/ProtoV2/Scripts/MatchCountdown.cs</code></li>\n                    <li><code>Assets/ProtoV2/Scripts/MatchManager.cs</code></li>\n                    <li><code>Assets/ProtoV2/Prefabs/PlayerPrefab.prefab</code> (4 new GO+Transform+MMF_Player blocks)</li>\n                    <li><code>Assets/ProtoV2/Scenes/MatchScene.unity</code> (4 MMF_Player feedbacks populated)</li>\n                  </ul>\n                  <p>---</p>\n                  <h3>Obi Fluid Memory Leak — Continued Investigation (2026-03-29)</h3>\n                  <p>Continued from <code>2026-03-28_ObiFluid_MemoryLeak_Fix.md</code>. Previous session patched the rendering-side leak (VolumePass materials, MaterialPropertyBlock, AsyncGPUReadback closures). This session found and addressed the simulation-side leak.</p>\n                  <p>---</p>\n                  <h3>Monitoring Setup</h3>\n                  <p>PowerShell script at <code>C:/Users/ReconUnPro/AppData/Local/Temp/monitor_mem2.ps1</code> — polls every 5s:</p>\n                  <ul>\n                    <li>Game process working set (MB) via <code>Get-Process</code></li>\n                    <li>System RAM available / used / % via <code>Get-CimInstance Win32_OperatingSystem</code></li>\n                  </ul>\n                  <p>---</p>\n                  <h3>Isolation Test Results</h3>\n                  <h3>Build #006 — All Obi Rendering Disabled</h3>\n                  <p>Disabled three layers to fully strip rendering:</p>\n                  <p>1. Removed <code>ObiFluidRendererFeature</code> from <code>m_RendererFeatures</code> in <code>PC_Renderer.asset</code></p>\n                  <p>2. <code>ObiParticleRenderer</code> → <code>m_Enabled: 0</code> on <code>BloodEmitter.prefab</code></p>\n                  <p>3. <code>ObiFluidSurfaceMesher</code> → <code>m_Enabled: 0</code> on <code>BloodEmitter.prefab</code></p>\n                  <p><strong>Result:</strong> Memory still grew at ~161 MB/s. Flush/scene reload gave no relief.</p>\n                  <p><strong>Conclusion:</strong> Leak exists on BOTH sides:</p>\n                  <ul>\n                    <li>Rendering side: ~320 MB/s (patched in prior session, confirmed by rate drop)</li>\n                    <li>Simulation side: ~161 MB/s (still present — this session's target)</li>\n                  </ul>\n                  <p>---</p>\n                  <h3>Patches Applied This Session</h3>\n                  <h3>Patch 3 — `ObiSolver.PushActiveParticles()` (previously applied)</h3>\n                  <p>Pre-allocate <code>activeParticles</code> to <code>allocParticleCount</code> before clear so <code>EnsureCapacity</code> never fires mid-emission.</p>\n                  <h3>Patch 4 — `ComputeSolverImpl.SetActiveParticles()` (previously applied)</h3>\n                  <p>Guard: only call <code>AsComputeBuffer</code> if buffer is null. Otherwise <code>UploadFullCapacity()</code>.</p>\n                  <h3>Patch 5 — `ObiSolver.PushSimplices()`</h3>\n                  <p><strong>File:</strong> <code>Assets/Obi/Scripts/Common/Solver/ObiSolver.cs</code></p>\n                  <p>Added before <code>simplices.Clear()</code>:</p>\n                  <p><strong>Why:</strong> <code>dirtySimplices</code> is set every time a particle is activated (every emission frame). Without pre-allocation, <code>EnsureCapacity</code> fires repeatedly as the active count grows, each time doubling capacity and nulling <code>m_ComputeBuffer</code>.</p>\n                  <h3>Patch 6 — `ComputeSolverImpl.SetSimplices()`</h3>\n                  <p><strong>File:</strong> <code>Assets/Obi/Scripts/Common/Backends/Compute/Solver/ComputeSolverImpl.cs</code></p>\n                  <p>Replaced unconditional <code>AsComputeBuffer</code> calls on <code>simplices</code> (line 515) and <code>cellCoords</code> (line 516):</p>\n                  <p><strong>Result of builds #006-#007:</strong> Memory still grew at ~161 MB/s. These patches were correct but insufficient — the ROOT CAUSE was elsewhere.</p>\n                  <p>---</p>\n                  <h3>Root Cause Found — Bloated Blueprint Capacity</h3>\n                  <h3>The Discovery</h3>\n                  <p>Deep Obi source analysis by Opus architect agent identified the actual culprit.</p>\n                  <p><strong><code>BloodFluid.asset</code> had <code>capacity: 20000</code> per emitter.</strong></p>\n                  <p>With 9 emitters active (3 emitters/floor × 3 floors), the solver pre-allocates:</p>\n                  <ul>\n                    <li>Total particle slots: 9 × 20,000 = <strong>180,000</strong></li>\n                    <li><code>positions.count</code> = 180,000 (used by <code>SetCapacity</code>)</li>\n                  </ul>\n                  <p>This caused <code>ComputeParticleGrid.SetCapacity()</code> to create:</p>\n                  <p>| Buffer | Size |</p>\n                  <p>|---|---|</p>\n                  <p>| <code>neighbors</code> (180k × 2 × 128 neighbors × 4B) | <strong>184 MB</strong> |</p>\n                  <p>| All 20+ grid buffers total | <strong>~230 MB</strong> |</p>\n                  <p>| <code>colliderContacts</code> readback buffer | <strong>~46 MB</strong> |</p>\n                  <p>| 26 particle arrays in <code>ParticleCountChanged</code> | <strong>~170 MB</strong> |</p>\n                  <p><strong>~650 MB allocated at match start</strong> — before a single particle is emitted.</p>\n                  <p>The D3D12 driver pools these on disposal (never returns to OS), so repeated SetCapacity calls accumulate permanently. <code>colliderContacts.Readback()</code> in <code>ObiSolver.RequestReadback()</code> fires every frame (whenever <code>OnCollision != null</code>, which our scripts always satisfy), staging a ~46 MB readback buffer per frame into D3D12's READBACK heap.</p>\n                  <h3>Why 20,000 Was Wrong</h3>\n                  <p>Our <code>ObiEmitter</code> runs in burst mode:</p>\n                  <ul>\n                    <li>7 particles/sec × 1.5s burst every 5s = ~2.1 particles/sec average</li>\n                    <li>Particle lifespan: 60s</li>\n                    <li>Peak live particles per emitter: 2.1 × 60 = <strong>~126</strong></li>\n                  </ul>\n                  <p>20,000 capacity = <strong>158× overprovision</strong>. The default Obi blueprint value was never adjusted for our actual usage.</p>\n                  <h3>The Fix</h3>\n                  <p><strong><code>Assets/ProtoV2/Blueprints/BloodFluid.asset</code> line 1559:</strong></p>\n                  <p>200 gives 1.6× headroom over peak (126 live particles). With 9 emitters:</p>\n                  <ul>\n                    <li>Total particle slots: 9 × 200 = <strong>1,800</strong> (vs 180,000)</li>\n                    <li><code>neighbors</code> buffer: <strong>1.8 MB</strong> (vs 184 MB) — 100× reduction</li>\n                    <li><code>colliderContacts</code> readback: <strong>~460 KB</strong> (vs 46 MB) — 100× reduction</li>\n                  </ul>\n                  <p>---</p>\n                  <h3>Secondary Root Cause — ObiNativeList Finalizer (Scene Reload Doesn't Help)</h3>\n                  <p><code>ObiNativeList.~ObiNativeList()</code> calls <code>DisposeOfComputeBuffer()</code> from the GC finalizer thread. <code>GraphicsBuffer.Dispose()</code> must run on the main thread — called from the wrong thread, it silently fails. GPU buffers are permanently orphaned and survive scene reload.</p>\n                  <p>This explains why Flush/scene restart never released memory — not a leak per se but a one-time orphan per solver lifetime.</p>\n                  <p><strong>Status:</strong> Not patched yet. Lower priority now that capacity is fixed.</p>\n                  <p>---</p>\n                  <h3>Build Log</h3>\n                  <p>| Build | Change | Sim Leak Rate | Notes |</p>\n                  <p>|---|---|---|---|</p>\n                  <p>| #004 (prev) | Rendering patches | ~481 MB/s | Rendering still enabled |</p>\n                  <p>| #005 | m_Active: 0 attempt | ~481 MB/s | Wrong YAML field — fluid still rendered |</p>\n                  <p>| #006 | All rendering disabled | ~161 MB/s | Confirmed sim-side leak |</p>\n                  <p>| #007 | SetSimplices patch | ~161 MB/s | Patch correct but not root cause |</p>\n                  <p>| #008 | capacity: 200 + SetSimplices | ~134 MB/s | Baseline polluted (monitoring started mid-match at 20 GB); capacity patches correct but D3D12 root cause not yet identified |</p>\n                  <p>| #009 | ObiSolver disabled | ~135 MB/s (polluted) / flat after reboot | Confirmed leak stops when match ends even without Obi; polluted D3D12 baseline made rate unreliable |</p>\n                  <p>| #010 | ObiSolver disabled + D3D11 | <strong>~0 MB/s</strong> | Flat 1280 MB throughout full match — confirmed D3D12 deferred-release pool is root cause |</p>\n                  <p>| #011 | Full Obi re-enabled + D3D11 | <strong>~0.1 MB/s</strong> | FIXED — 1337→1347 MB over 90s. Stable. |</p>\n                  <p>---</p>\n                  <h3>Root Cause (Final)</h3>\n                  <p>The leak was <strong>D3D12-specific deferred-release pool behaviour</strong>, not a true memory leak in code.</p>\n                  <ul>\n                    <li>D3D12: <code>GraphicsBuffer.Dispose()</code> queues the buffer for deferred release. The driver returns memory to an internal pool, NOT to the OS. New allocations commit fresh OS pages instead of reusing pooled ones. Pool grows monotonically for the lifetime of the process.</li>\n                    <li>D3D11: Disposed resources are returned to the driver pool immediately and reused for new allocations. Working set stays flat.</li>\n                  </ul>\n                  <p>Obi's emit/die particle lifecycle creates a small but steady stream of new <code>GraphicsBuffer</code> allocations per frame (<code>SetSimplices</code>, readbacks). On D3D11 these are reused. On D3D12 they permanently expand the pool.</p>\n                  <p><strong>Fix applied:</strong> <code>ProjectSettings.asset</code> — Standalone Windows graphics API forced to Direct3D11 (<code>m_APIs: 02000000</code>, <code>m_Automatic: 0</code>).</p>\n                  <p>---</p>\n                  <h3>What Didn't Work / Lessons</h3>\n                  <ul>\n                    <li><code>m_Enabled: 0</code> on a URP <code>ScriptableRendererFeature</code> — WRONG field. URP checks <code>m_Active</code>, not <code>m_Enabled</code>.</li>\n                    <li>Removing ObiFluidRendererFeature from <code>m_RendererFeatures</code> — correct way to disable URP features in YAML.</li>\n                    <li><code>SetSimplices</code>/<code>SetActiveParticles</code> guards — correct patches but not the root cause. The leak was D3D12 pool behaviour, not allocation frequency or size.</li>\n                    <li>Capacity 20000→200 — correct and reduces one-time static allocation by 100×, but doesn't fix D3D12 pool growth.</li>\n                    <li>Polluted D3D12 baseline (no reboot between test builds) made rate measurements unreliable across builds. Always reboot when comparing rates.</li>\n                    <li>Source-only analysis hit limits — binary isolation (disable ObiSolver, then switch API) was faster than reading code.</li>\n                  </ul>\n                  <p>---</p>\n                  <h3>Remaining Items</h3>\n                  <ul>\n                    <li>[x] Re-enable rendering (ObiFluidRendererFeature, ObiParticleRenderer, ObiFluidSurfaceMesher)</li>\n                    <li>[x] Verify memory is stable with rendering re-enabled — CONFIRMED 0.1 MB/s</li>\n                    <li>[x] Force D3D11 for all Standalone builds — <code>ProjectSettings.asset</code> permanently set (<code>m_APIs: 02000000</code>, <code>m_Automatic: 0</code>)</li>\n                    <li>[ ] Fix ObiNativeList finalizer thread issue (GPU buffer orphaning on scene reload) — lower priority, one-time per session; mitigated by D3D11</li>\n                    <li>[ ] Update <code>maxSurfaceChunks</code> if needed now that particle count is much smaller</li>\n                  </ul>\n                  <p>---</p>\n                  <h3>Status: RESOLVED (2026-03-29)</h3>\n                  <p>Memory leak investigation is complete. Game is stable at ~0.1 MB/s (effectively flat). All Standalone builds will use Direct3D11 permanently for as long as Obi Fluid is in the project. Proceeding to next development phase.</p>\n                  <p>---</p>\n                  <h3>2026-03-31 — Centralised Audio Management Panel</h3>\n                  <h3>Summary</h3>\n                  <p>Added a <code>GameAudioData</code> ScriptableObject as a single source of truth for all 22 audio clip slots across the game. Includes a rich custom Inspector panel with category foldouts, clip-count badge, preview buttons, and auto-link tools.</p>\n                  <p>---</p>\n                  <h3>Problem</h3>\n                  <p>Audio clips were scattered across 5 different components on 4 different prefabs/GOs:</p>\n                  <ul>\n                    <li><code>AudioManager</code> (MatchScene GO) — 9 clips</li>\n                    <li><code>PlayerAudioSource</code> (PlayerPrefab) — 5 clips</li>\n                    <li><code>AltarAudioSource</code> (Altar prefab) — 3 clips</li>\n                    <li><code>BloodEmitterAudioSource</code> (BloodEmitter prefab) — 2 clips</li>\n                    <li><code>UIAudioManager</code> (DontDestroyOnLoad GO) — 5 clips</li>\n                  </ul>\n                  <p>To reassign a clip you had to hunt through 4 prefabs. No way to see the full audio inventory at a glance.</p>\n                  <p>---</p>\n                  <h3>Solution</h3>\n                  <h3>New Files</h3>\n                  <p><strong><code>Assets/ProtoV2/Scripts/Audio/GameAudioData.cs</code></strong> — <code>ScriptableObject</code> holding all 22 <code>AudioClip</code> fields + <code>sfxGroup</code> / <code>uiGroup</code> <code>AudioMixerGroup</code> refs, grouped by category:</p>\n                  <ul>\n                    <li>Match/Countdown, Floor Scroll, Match Outcome, Outlast Ticker, Floor Impact</li>\n                    <li>Player, Altar, Blood Emitter, UI</li>\n                  </ul>\n                  <p><strong><code>Assets/ProtoV2/Scripts/Editor/GameAudioDataEditor.cs</code></strong> — Custom Inspector with:</p>\n                  <ul>\n                    <li>Bold header \"Ritual & Ruin — Audio Data\"</li>\n                    <li><code>HelpBox</code> badge: \"X / 22 clips assigned\" (warning if incomplete)</li>\n                    <li>Per-category colour-coded foldouts (persisted via EditorPrefs) each showing <code>assigned/total</code></li>\n                    <li>Every slot: object field + <code>▶</code> preview button (AudioUtil reflection, fallback safe)</li>\n                    <li><strong>\"Find & Link Clips from SFX Folder\"</strong> button — scans <code>Assets/ProtoV2/Audio/SFX/</code> and auto-assigns by filename pattern matching</li>\n                    <li><strong>\"Find & Link Mixer Groups\"</strong> button — loads <code>GameAudioMixer</code> from Resources and assigns SFX + UI groups</li>\n                  </ul>\n                  <p><strong><code>Assets/ProtoV2/Scripts/Editor/GameAudioDataWizard.cs</code></strong> — Menu items under <code>Tools/Ritual & Ruin/Audio/</code>:</p>\n                  <ul>\n                    <li><strong>Create GameAudioData Asset</strong> — creates <code>Assets/ProtoV2/Audio/GameAudioData.asset</code>, selects + pings it</li>\n                    <li><strong>Auto-Link Clips & Mixers</strong> — one-shot auto-fills the asset from the SFX folder + mixer, logs all assignments</li>\n                  </ul>\n                  <h3>Modified Files (backward-compatible)</h3>\n                  <p>Each of the 5 audio components gained:</p>\n                  <p>1. <code>[Header(\"Audio Data\")] [SerializeField] private GameAudioData _audioData;</code> as the first serialized field</p>\n                  <p>2. An if-block at the top of <code>Awake()</code> that copies clips from <code>_audioData</code> into the existing private fields when assigned</p>\n                  <p>Components affected:</p>\n                  <ul>\n                    <li><code>AudioManager.cs</code> — 9 clips + sfxGroup</li>\n                    <li><code>PlayerAudioSource.cs</code> — 5 clips + sfxGroup</li>\n                    <li><code>AltarAudioSource.cs</code> — 3 clips + sfxGroup</li>\n                    <li><code>BloodEmitterAudioSource.cs</code> — 2 clips + sfxGroup</li>\n                    <li><code>UIAudioManager.cs</code> — 5 clips + uiGroup</li>\n                  </ul>\n                  <p><strong>Backward compatible</strong>: if <code>_audioData</code> is null, all individual Inspector-assigned clips continue to work unchanged.</p>\n                  <p>---</p>\n                  <h3>How to Set Up</h3>\n                  <p>1. <code>Tools/Ritual & Ruin/Audio/Create GameAudioData Asset</code> — creates the asset</p>\n                  <p>2. Select it in Project → Inspector shows the full panel</p>\n                  <p>3. Click <strong>\"Find & Link Clips from SFX Folder\"</strong> + <strong>\"Find & Link Mixer Groups\"</strong> to auto-fill</p>\n                  <p>4. Assign the asset to the <code>_audioData</code> slot on: AudioManager (MatchScene), UIAudioManager (MainMenu scene), PlayerPrefab, Altar prefab, BloodEmitter prefab</p>\n                  <p>Or use <code>Tools/Ritual & Ruin/Audio/Auto-Link Clips & Mixers</code> to do steps 2+3 from a menu item.</p>\n                  <p>---</p>\n                  <h3>Files Changed</h3>\n                  <p>| File | Change |</p>\n                  <p>|---|---|</p>\n                  <p>| <code>Assets/ProtoV2/Scripts/Audio/GameAudioData.cs</code> | NEW — ScriptableObject, 22 clips + 2 mixer groups |</p>\n                  <p>| <code>Assets/ProtoV2/Scripts/Editor/GameAudioDataEditor.cs</code> | NEW — Custom Inspector panel |</p>\n                  <p>| <code>Assets/ProtoV2/Scripts/Editor/GameAudioDataWizard.cs</code> | NEW — Create + auto-link menu items |</p>\n                  <p>| <code>Assets/ProtoV2/Scripts/Audio/AudioManager.cs</code> | +<code>_audioData</code> field + Awake copy block |</p>\n                  <p>| <code>Assets/ProtoV2/Scripts/Audio/PlayerAudioSource.cs</code> | +<code>_audioData</code> field + Awake copy block |</p>\n                  <p>| <code>Assets/ProtoV2/Scripts/Audio/AltarAudioSource.cs</code> | +<code>_audioData</code> field + Awake copy block |</p>\n                  <p>| <code>Assets/ProtoV2/Scripts/Audio/BloodEmitterAudioSource.cs</code> | +<code>_audioData</code> field + Awake copy block |</p>\n                  <p>| <code>Assets/ProtoV2/Scripts/Audio/UIAudioManager.cs</code> | +<code>_audioData</code> field + Awake copy block |</p>\n                  <p>---</p>\n                  <h3>2026-03-31 — Obi Rope + Obi Softbody Jellyfish Upgrade</h3>\n                  <h3>What Was Done</h3>\n                  <p>Replaced the procedural LineRenderer spring-chain tentacles with proper <strong>Obi Rope</strong> physics tentacles, and added an <strong>Obi Softbody</strong> jelly core system. Both packages (Obi Rope 7.x, Obi Softbody 7.x) were already imported by the developer.</p>\n                  <p>---</p>\n                  <h3>Files Changed</h3>\n                  <h3>`Assets/ProtoV2/Scripts/JellyfishVisuals.cs` — Full rewrite (tentacle system only)</h3>\n                  <p><strong>Removed:</strong></p>\n                  <ul>\n                    <li>All LineRenderer fields: <code>_tentacles</code>, <code>_tentacleMaterials</code>, <code>_segmentPositions</code>, <code>_rimOffsetsLocal</code></li>\n                    <li>Inspector params: <code>segmentCount</code>, <code>segmentLength</code>, <code>dampFactor</code>, <code>startWidth</code>, <code>endWidth</code>, <code>swayAmplitude</code>, <code>swayFrequency</code></li>\n                    <li>Methods: <code>BuildTentacles()</code>, <code>UpdateTentacles()</code>, <code>BuildTentacleMaterial()</code></li>\n                  </ul>\n                  <p><strong>Added:</strong></p>\n                  <ul>\n                    <li><code>[SerializeField] ObiSolver _solver</code> — auto-found via <code>FindObjectOfType</code> if null; tentacles skipped gracefully if solver unavailable (bell squish + hover bob still work)</li>\n                    <li>Inspector params: <code>ropeLength=0.9</code>, <code>ropeVisualThickness=0.05</code>, <code>ropeBendCompliance=0.01</code>, <code>ropeParticleCount=8</code></li>\n                    <li>Runtime arrays: <code>_ropes</code>, <code>_blueprints</code>, <code>_anchorTransforms</code>, <code>_ropeMaterials</code></li>\n                    <li><code>BuildRimOffsets()</code> — same XZ rim circle math as before</li>\n                    <li><code>BuildObiRopeTentacles()</code> — creates 6 ObiRope actors at Start(), each parented under ObiSolver</li>\n                    <li><code>UpdateAnchorTransforms()</code> — updates anchor Transform world positions each frame (same formula as old anchor calc: world Y from VisualRoot + rim XZ from root direction)</li>\n                    <li><code>CreateRopeMaterial()</code> — URP/Unlit transparent material, team-colored</li>\n                  </ul>\n                  <p><strong>Unchanged:</strong> <code>UpdateHoverBob()</code>, <code>UpdateBellSquish()</code>, <code>ApplyEvolutionTint()</code>, <code>SetTentacleColor()</code>, all evolution/color fields, <code>OnDestroy()</code> cleanup pattern.</p>\n                  <p><strong>Rope setup per tentacle:</strong></p>\n                  <p>1. Anchor Transform child of root GO (NOT VisualRoot — avoids inheriting bell tilt)</p>\n                  <p>2. ObiRopeBlueprint: 2 control points (root at 0,0,0 → tip at 0,-length,0), tapered thickness (tip = 40% of root), root color opaque → tip alpha=0</p>\n                  <p>3. ObiRope + ObiPathSmoother + ObiRopeExtrudedRenderer (DefaultRopeSection)</p>\n                  <p>4. ObiParticleAttachment.Static on groups[0] → anchor transform</p>\n                  <p>5. Parent under solver LAST (triggers AddToSolver)</p>\n                  <p>---</p>\n                  <h3>`Assets/ProtoV2/Scripts/JellyfishSoftCore.cs` — New</h3>\n                  <p>ObiSoftbody \"jelly interior\" component. Add to PlayerPrefab root. Requires a pre-baked blueprint (run wizard below).</p>\n                  <p>At Start(): creates a sphere-shaped ObiSoftbody GO under the solver, dynamically pin-attached to the character root via <code>ObiParticleAttachment.Dynamic</code> with configurable <code>_compliance</code> (default 0.002 — elastic spring lag). Rendered with a translucent blue sphere.</p>\n                  <p>Exposes:</p>\n                  <ul>\n                    <li><code>PulseSquish(float inwardSpeed)</code> — applies inward radial velocity to all particles on pulse</li>\n                    <li><code>SetColor(Color)</code> — evolution tinting</li>\n                    <li><code>IsReady</code> — safe call guard</li>\n                  </ul>\n                  <p>---</p>\n                  <h3>`Assets/ProtoV2/Scripts/Editor/JellyfishSoftCoreSetupWizard.cs` — New</h3>\n                  <p><strong>Menu: <code>Ritual & Ruin / Setup Jellyfish Soft Core</code></strong></p>\n                  <p>One-click editor wizard that:</p>\n                  <p>1. Gets Unity's built-in sphere mesh via <code>GameObject.CreatePrimitive(PrimitiveType.Sphere)</code></p>\n                  <p>2. Creates <code>ObiSoftbodyBlueprint</code>, assigns mesh, calls <code>GenerateImmediate()</code></p>\n                  <p>3. Saves blueprint to <code>Assets/ProtoV2/SoftbodyBlueprints/JellyfishCoreSoftbody.asset</code></p>\n                  <p>4. Opens PlayerPrefab via <code>EditPrefabContentsScope</code>, adds <code>JellyfishSoftCore</code> to root, wires blueprint</p>\n                  <p>---</p>\n                  <h3>How to Use After Compilation</h3>\n                  <h3>Obi Rope Tentacles (automatic)</h3>\n                  <ul>\n                    <li>Assign ObiSolver reference on JellyfishVisuals in PlayerPrefab Inspector, OR leave null (auto-found at runtime)</li>\n                    <li>Enter Play mode → 6 ObiRope tentacles simulate under the solver, physically trailing behind character movement</li>\n                  </ul>\n                  <h3>Obi Softbody Jelly Core (opt-in)</h3>\n                  <p>1. Wait for scripts to compile</p>\n                  <p>2. Run <strong>Ritual & Ruin / Setup Jellyfish Soft Core</strong> from the Unity menu</p>\n                  <p>3. Enter Play mode → translucent sphere lags behind character with elastic follow</p>\n                  <p><strong>Tuning parameters (JellyfishSoftCore Inspector):</strong></p>\n                  <ul>\n                    <li><code>_compliance</code>: 0.001 (tight) → 0.01 (very sloshy)</li>\n                    <li><code>_coreOffset</code>: default (0, 1.5, 0) — positions core inside bell</li>\n                    <li><code>_coreScale</code>: default 0.35 — sphere radius</li>\n                    <li><code>_coreColor</code>: default translucent blue-white (0.5, 0.85, 1, 0.25)</li>\n                  </ul>\n                  <p><strong>Tuning parameters (JellyfishVisuals Inspector):</strong></p>\n                  <ul>\n                    <li><code>ropeLength</code>: 0.9 — tentacle length</li>\n                    <li><code>ropeVisualThickness</code>: 0.05 — cross-section radius</li>\n                    <li><code>ropeBendCompliance</code>: 0.01 — stiffness (0=rigid, 0.1=very floppy)</li>\n                    <li><code>ropeParticleCount</code>: 8 — simulation resolution</li>\n                  </ul>\n                  <p>---</p>\n                  <h3>Architecture Notes</h3>\n                  <ul>\n                    <li>Rope GOs are parented under ObiSolver, NOT under the character. Anchor Transforms (children of character root) follow the character each frame; ObiParticleAttachment.Static pins rope particle 0 to each anchor.</li>\n                    <li>Anchor Transforms are children of the root (not VisualRoot) so they don't inherit pour tilt or bell squish rotation.</li>\n                    <li><code>OnDestroy()</code> cleans up all rope GOs, blueprint ScriptableObjects (DestroyImmediate), materials, and anchor GOs — no leaks on respawn/rematch.</li>\n                    <li>If ObiSolver not found at Start, bell squish and hover bob still work — only tentacles are skipped.</li>\n                    <li>JellyfishSoftCore is fully optional. No changes to JellyfishVisuals required for softbody to work.</li>\n                  </ul>\n                  <p>---</p>\n                  <h3>Design Vault Reference</h3>\n                  <ul>\n                    <li>Asset Catalog Tier 1: Obi Rope ✅ implemented, Obi Softbody ✅ implemented</li>\n                    <li>Jellyfish Visuals confirmed doc: \"Future: replace with ObiRopes\" ✅ done</li>\n                  </ul>\n                  <p>---</p>\n                  <h3>2026-04-03 — Tentacle Revert: LineRenderer Spring-Chain</h3>\n                  <h3>What Changed</h3>\n                  <p>Reverted jellyfish tentacles from ObiRope back to LineRenderer spring-chain.</p>\n                  <p><strong>Root cause for revert:</strong> ObiRope tentacles are physical actors — on every bell pulse the VisualRoot squishes, which moves the ObiParticleAttachment anchor, causing particles to bounce violently. The tentacles should trail softly, not react to the bell pulse physics.</p>\n                  <h3>Implementation</h3>\n                  <h3>JellyfishVisuals.cs — full rewrite</h3>\n                  <ul>\n                    <li>6 LineRenderer tentacles, 6 segments each</li>\n                    <li>Spring chain: segment 0 snaps to anchor, segments 1+ lerp toward <code>(prev + Vector3.down * segLen)</code> then distance-constrained to fixed length</li>\n                    <li><strong>Auto-scaling:</strong> all size values multiplied by <code>transform.lossyScale.x</code> at Start() so tentacles look correct at any character scale (match=0.25, lobby=0.69)</li>\n                    <li>Inspector values are scale=1 normalized</li>\n                  </ul>\n                  <h3>Prefab values (scale=1 normalized)</h3>\n                  <p>| Field | Value | World value @ scale=0.25 |</p>\n                  <p>|---|---|---|</p>\n                  <p>| rimRadius | 1.3 | 0.325 |</p>\n                  <p>| rimY | 1.5 | 0.375 (anchor above floor) |</p>\n                  <p>| segmentLength | 0.25 | 0.0625/segment, 0.375 total = reaches floor |</p>\n                  <p>| startWidth | 0.6 | 0.15 |</p>\n                  <p>| endWidth | 0.16 | 0.04 |</p>\n                  <p><strong>Key insight on segmentLength:</strong> Originally set to 0.6 (= 0.9 world units total at match scale) — tentacles extended 0.525 units below floor, making only ~2 segments visible. Corrected to 0.25 (= 0.375 world units total) so all 6 segments are visible above floor. At lobby scale 0.69: 0.25 × 0.69 × 6 = 1.035 world units = exactly matches anchor height. Both scenes auto-balance.</p>\n                  <h3>TentacleSetupWizard.cs</h3>\n                  <p>Added \"Ritual & Ruin/Cleanup Jellyfish Tentacles (Revert to LineRenderer)\" menu item that removes <code>TentacleSolver</code> GO and <code>TentacleAnchor_*</code> from VisualRoot. ObiRope setup code kept shelved for future reference.</p>\n                  <h3>Visual Result</h3>\n                  <p>Tentacles appear as a radial fringe of colored lines immediately around each jellyfish body. From the isometric top-down camera angle, downward-hanging tentacles are foreshortened — appears as a small colored cluster rather than long dangling appendages. Correctly attached to characters, correctly auto-scaled, correctly team-colored.</p>\n                  <p>---</p>\n                  <h3>2026-04-04 — Tilt Control in Rebind UI + In-Match Menu Hints</h3>\n                  <h3>What Changed</h3>\n                  <p>Three pending gaps from the 2026-03-23 manual tilt session completed:</p>\n                  <p>1. Tilt (right stick) added to all rebind UIs</p>\n                  <p>2. Auto-tilt toggle wiring completed (PlayerMenuController + PlayerSettingsPanel)</p>\n                  <p>3. Per-player menu hint text added to in-match HUD and settings panel</p>\n                  <p>---</p>\n                  <h3>Tilt in Rebind UIs</h3>\n                  <p>Tilt was fully implemented in the input system but never surfaced to players as a rebindable control.</p>\n                  <h3>Files changed</h3>\n                  <p><strong><code>InputRebindMenuUI.cs</code></strong></p>\n                  <ul>\n                    <li>Added <code>\"Tilt\"</code> to <code>rebindableActions</code>. The UGUI lobby rebind panel now shows a Tilt row for controller players. Keyboard players see no row (Tilt has no keyboard binding — skipped automatically by <code>GetBindingIndexForControlScheme</code> returning -1).</li>\n                  </ul>\n                  <p><strong><code>PlayerSettingsPanel.cs</code></strong></p>\n                  <ul>\n                    <li>Added <code>\"Tilt\"</code> to <code>rebindableActions</code>. Same behavior in the in-game settings panel.</li>\n                  </ul>\n                  <p><strong><code>InputRebindUIController.cs</code></strong> (UI Toolkit lobby panel)</p>\n                  <ul>\n                    <li><code>BindingNames</code> / <code>ActionMappings</code>: added <code>\"tilt\"</code> / <code>\"Tilt\"</code> at index 6</li>\n                    <li><code>ControllerPresetBindings</code>: added tilt as 4th element per preset:</li>\n                    <li>L-Stick + Buttons → <code>rightStick</code></li>\n                    <li>L-Stick + Triggers → <code>rightStick</code></li>\n                    <li>R-Stick + Buttons → <code>leftStick</code> (rightStick already used for Move in this preset)</li>\n                    <li>D-Pad + Buttons → <code>rightStick</code></li>\n                    <li><code>ApplyPreset()</code> controller branch: calls <code>ApplyControllerMovePreset(tiltAction, presetPaths[3])</code> — correct because Tilt is <code>Value/Vector2</code> (same structure as Move)</li>\n                  </ul>\n                  <p>---</p>\n                  <h3>Auto-Tilt Toggle Wiring</h3>\n                  <p><code>PlayerMenuController</code> and <code>PlayerSettingsPanel</code> code was complete since 2026-03-23. The missing piece was editor wiring. The existing <code>PlayerMenuSetupWizard</code> (Tools > Player Menu Setup) confirmed everything was already in place from a prior run:</p>\n                  <p>Toggle behavior: visible only for controller players (keyboard always uses auto-tilt; hidden for them). Players access it via MenuOpen (Start/Escape) → Settings panel.</p>\n                  <p>---</p>\n                  <h3>Per-Player Menu Hint Text</h3>\n                  <p>New UI prompt system so players know how to open/close the per-player settings panel during a match.</p>\n                  <h3>`PlayerMenuController.cs`</h3>\n                  <ul>\n                    <li>Added <code>[SerializeField] TextMeshProUGUI menuHintText</code></li>\n                    <li><code>Start()</code>: sets initial text, subscribes to <code>PlayerSetup.OnInputModeChanged</code></li>\n                    <li><code>UpdateHintText()</code> sets text based on current state:</li>\n                  </ul>\n                  <p>| State | Controller | Keyboard |</p>\n                  <p>|---|---|---|</p>\n                  <p>| Menu closed | <code>START — Settings</code> | <code>ESC — Settings</code> |</p>\n                  <p>| Menu open | <code>START — Close Settings</code> | <code>ESC — Close Settings</code> |</p>\n                  <p>| Waiting for controller | <code>Waiting for controller…</code> | — |</p>\n                  <ul>\n                    <li>Fires on <code>OpenMenu()</code>, <code>CloseMenu()</code>, and any device change event</li>\n                  </ul>\n                  <h3>`PlayerSettingsPanel.cs`</h3>\n                  <ul>\n                    <li>Added <code>[SerializeField] TextMeshProUGUI instructionText</code></li>\n                    <li>Set in <code>Show()</code> based on player's input mode:</li>\n                    <li>Controller: <code>START or B — Close</code></li>\n                    <li>Keyboard: <code>ESC — Close</code></li>\n                  </ul>\n                  <h3>Unity wiring — `MenuHintWiringWizard.cs` (new editor script)</h3>\n                  <p>Runs via <strong>Tools > Wire Menu Hint Text</strong>. One-shot, rerunnable.</p>\n                  <ul>\n                    <li><strong>PlayerPrefab</strong>: Created <code>MenuHintText</code> TMP child under <code>BarCanvas</code>, anchored below the health bar. Font size 3 (world-space canvas), 65% opacity white, centre-aligned. Wired to <code>PlayerMenuController.menuHintText</code>.</li>\n                    <li><strong>LobbyScene / PlayerSettingsPanelCanvas/PanelRoot</strong>: Created <code>InstructionText</code> TMP anchored to panel bottom, font size 13, grey. Wired to <code>PlayerSettingsPanel.instructionText</code>.</li>\n                    <li>LobbyScene saved.</li>\n                  </ul>"
    }
  ],
  "processed_files": {
    "2026-01-22_ControllerInputBindingFix.md": {
      "md5": "",
      "entry_id": "catchup"
    },
    "2026-02-05_ScrollingFloorSystem_UnitySetupGuide.md": {
      "md5": "",
      "entry_id": "catchup"
    },
    "2026-02-05_ScrollingFloorSystem.md": {
      "md5": "",
      "entry_id": "catchup"
    },
    "2026-02-14_PillarFixAndHazardAlignment.md": {
      "md5": "",
      "entry_id": "catchup"
    },
    "2026-02-21_LiquidifyRenameAndAlphaPlan.md": {
      "md5": "",
      "entry_id": "catchup"
    },
    "2026-02-24_UIStyleDirectionAndTransformPlanFix.md": {
      "md5": "",
      "entry_id": "catchup"
    },
    "2026-02-26_UnifiedBarEvolutionGrowth.md": {
      "md5": "",
      "entry_id": "catchup"
    },
    "2026-03-05_AlphaPlanDocumentSplit.md": {
      "md5": "",
      "entry_id": "catchup"
    },
    "2026-03-10_AlphaEditorWiring_Complete.md": {
      "md5": "",
      "entry_id": "catchup"
    },
    "2026-03-11_FloorVisibilityAndBoundaryWalls.md": {
      "md5": "",
      "entry_id": "catchup"
    },
    "2026-03-14_MatchStartFix_VisualPolish.md": {
      "md5": "",
      "entry_id": "catchup"
    },
    "2026-03-15_EmitterIndicator_PlayerCrosshair.md": {
      "md5": "",
      "entry_id": "catchup"
    },
    "2026-03-15_JellyfishVisuals.md": {
      "md5": "",
      "entry_id": "catchup"
    },
    "2026-03-15_PouringMechanic_ImplementationPlan.md": {
      "md5": "",
      "entry_id": "catchup"
    },
    "2026-03-16_VisualPolish_ControllerFix.md": {
      "md5": "",
      "entry_id": "catchup"
    },
    "2026-03-18_BloodEmitterSettings.md": {
      "md5": "",
      "entry_id": "catchup"
    },
    "2026-03-19_AltarFillVisual_ObiColliderFix.md": {
      "md5": "",
      "entry_id": "catchup"
    },
    "2026-03-19_PlaytestPolishBatch3.md": {
      "md5": "",
      "entry_id": "catchup"
    },
    "2026-03-20_AudioSystem.md": {
      "md5": "",
      "entry_id": "catchup"
    },
    "2026-03-21_Player4ControllerFix.md": {
      "md5": "",
      "entry_id": "catchup"
    },
    "2026-03-22_MemoryLeaks_TerminalPhase_OutlastUI.md": {
      "md5": "",
      "entry_id": "catchup"
    },
    "2026-03-23_ManualTiltSystem_CarrierSpeed_MenuNavigation.md": {
      "md5": "",
      "entry_id": "catchup"
    },
    "2026-03-26_BuildFixes_ShaderNull_MemoryFlush_PauseMenu.md": {
      "md5": "",
      "entry_id": "catchup"
    },
    "2026-03-27_PinkMaterials_ShaderVariants.md": {
      "md5": "",
      "entry_id": "catchup"
    },
    "2026-03-27_PinkMaterialFix.md": {
      "md5": "",
      "entry_id": "catchup"
    },
    "2026-03-27_SettingsSystem.md": {
      "md5": "",
      "entry_id": "catchup"
    },
    "2026-03-28_SettingsVerification_AudioRouting_CLAUDERefactor.md": {
      "md5": "",
      "entry_id": "catchup"
    },
    "2026-03-28_BuildSystem_Versioning.md": {
      "md5": "",
      "entry_id": "catchup"
    },
    "2026-03-28_ObiFluid_MemoryLeak_DeepAnalysis.md": {
      "md5": "",
      "entry_id": "catchup"
    },
    "2026-03-28_ObiFluid_MemoryLeak_Fix.md": {
      "md5": "",
      "entry_id": "catchup"
    },
    "2026-03-29_AudioOptions_AssignedSlots.md": {
      "md5": "f7faed90f352e5404bddae82682a8c26",
      "entry_id": "2026-04-05"
    },
    "2026-03-29_AudioVariation_SFXOptions.md": {
      "md5": "f3252b4b6de5d1a71db3e8143b57f686",
      "entry_id": "2026-04-05"
    },
    "2026-03-29_EvolutionSizeFix_AssetCatalog_CleanupResolved.md": {
      "md5": "725020c6ee84f46b5c6697b2b2a661bc",
      "entry_id": "2026-04-05"
    },
    "2026-03-29_JellyfishSquish_IndicatorFix_ScrollFix.md": {
      "md5": "146f3fd8f174a6921f8d414dba8f7723",
      "entry_id": "2026-04-05"
    },
    "2026-03-29_MMFeedbacks_Integration.md": {
      "md5": "4c6fba91a97dcf5fb350ff5258cb4256",
      "entry_id": "2026-04-05"
    },
    "2026-03-29_ObiFluid_MemoryLeak_ContinuedInvestigation.md": {
      "md5": "b86465e91265899db94b218382e9c24a",
      "entry_id": "2026-04-05"
    },
    "2026-03-31_CentralisedAudioPanel.md": {
      "md5": "4487e896344be2f9e0da87b3b1dfad38",
      "entry_id": "2026-04-05"
    },
    "2026-03-31_ObiRope_ObiSoftbody_JellyfishUpgrade.md": {
      "md5": "117feb0fe81fbf1c468195c9b1a5a9fb",
      "entry_id": "2026-04-05"
    },
    "2026-04-03_TentacleRevert_LineRenderer.md": {
      "md5": "bba925b616792e556370a90f895abe90",
      "entry_id": "2026-04-05"
    },
    "2026-04-04_TiltControl_RebindUI_MenuHints.md": {
      "md5": "4cbd68183676a366aea552a3a609676b",
      "entry_id": "2026-04-05"
    },
    "2026-04-07_ChunkShader_ShadowFix_VisualPolish.md": {
      "md5": "2e6063660fbc194bb5b20c349190b666",
      "entry_id": "2026-04-12"
    }
  }
}